[{"type":"sprite","labels":[],"frames":[[1552,1440,367,132,207,84]],"path":"scene/Symbol1","hd":false},{"type":"sprite","labels":[],"frames":[[954,1664,240,72,120,36]],"path":"scene/Symbol1copy","hd":false},{"type":"sprite","labels":[],"frames":[[657,1774,186,54,91,27]],"path":"scene/Symbol8","hd":false},{"type":"sprite","labels":[],"frames":[[1,1,760,610,0,0],[763,1,760,610,0,0]],"path":"scene/back","hd":false},{"labels":[],"type":"clip","resources":["scene/buttons/btn_back_e"],"frames":[[[0,-5.5,-14.45,0,1,1,1,1,1,1]],[[0,-8.45,-17.4,0,1.1,1.1,1,1,1,1]]],"path":"scene/buttons/btn_back","instances":[[0,null]]},{"type":"sprite","labels":[],"frames":[[1734,1664,69,69,5,5]],"path":"scene/buttons/btn_back_e","hd":false},{"labels":[],"type":"clip","resources":["scene/buttons/btn_opt1"],"frames":[[[0,-4.5,-8.25,0,1,1,1,1,1,1]],[[0,-7.45,-11.2,0,1.1,1.1,1,1,1,1]]],"path":"scene/buttons/btn_m1_opt1","instances":[[0,null]]},{"labels":[],"type":"clip","resources":["scene/buttons/btn_opt2"],"frames":[[[0,-5,-8.25,0,1,1,1,1,1,1]],[[0,-7.95,-11.2,0,1.1,1.1,1,1,1,1]]],"path":"scene/buttons/btn_m1_opt2","instances":[[0,null]]},{"labels":[],"type":"clip","resources":["scene/buttons/btn_opt3"],"frames":[[[0,-5,-8.25,0,1,1,1,1,1,1]],[[0,-7.95,-11.2,0,1.1,1.1,1,1,1,1]]],"path":"scene/buttons/btn_m1_opt3","instances":[[0,null]]},{"labels":[],"type":"clip","resources":["scene/buttons/btn_opt4"],"frames":[[[0,-2.05,-8.25,0,1,1,1,1,1,1]],[[0,-5,-11.2,0,1.1,1.1,1,1,1,1]]],"path":"scene/buttons/btn_m1_opt4","instances":[[0,null]]},{"labels":[],"type":"clip","resources":["scene/buttons/btn_opt5"],"frames":[[[0,-5,-8.25,0,1,1,1,1,1,1]],[[0,-7.95,-11.2,0,1.1,1.1,1,1,1,1]]],"path":"scene/buttons/btn_m1_opt5","instances":[[0,null]]},{"labels":[],"type":"clip","resources":["scene/buttons/btn_opt6"],"frames":[[[0,-2,-8.3,0,1,1,1,1,1,1]],[[0,-4.95,-11.25,0,1.1,1.1,1,1,1,1]]],"path":"scene/buttons/btn_m1_opt6","instances":[[0,null]]},{"labels":[],"type":"clip","resources":["scene/buttons/btn_opt7"],"frames":[[[0,-5,-8.3,0,1,1,1,1,1,1]],[[0,-7.95,-11.25,0,1.1,1.1,1,1,1,1]]],"path":"scene/buttons/btn_m1_opt7","instances":[[0,null]]},{"labels":[],"type":"clip","resources":["scene/buttons/btn_opt1"],"frames":[[[0,-5.85,-8.25,0,1,1,1,1,1,1]],[[0,-8.8,-10.35,0,1.1,1.1,1,1,1,1]]],"path":"scene/buttons/btn_m2_opt1","instances":[[0,null]]},{"labels":[],"type":"clip","resources":["scene/buttons/btn_opt2"],"frames":[[[0,-4.35,-8.25,0,1,1,1,1,1,1]],[[0,-7.3,-11.2,0,1.1,1.1,1,1,1,1]]],"path":"scene/buttons/btn_m2_opt2","instances":[[0,null]]},{"labels":[],"type":"clip","resources":["scene/buttons/btn_opt3"],"frames":[[[0,-6.35,-8.25,0,1,1,1,1,1,1]],[[0,-9.3,-11.2,0,1.1,1.1,1,1,1,1]]],"path":"scene/buttons/btn_m2_opt3","instances":[[0,null]]},{"labels":[],"type":"clip","resources":["scene/buttons/btn_opt4"],"frames":[[[0,-6.1,-8.25,0,1,1,1,1,1,1]],[[0,-9.05,-11.2,0,1.1,1.1,1,1,1,1]]],"path":"scene/buttons/btn_m2_opt4","instances":[[0,null]]},{"labels":[],"type":"clip","resources":["scene/buttons/btn_opt5"],"frames":[[[0,-5.85,-8.25,0,1,1,1,1,1,1]],[[0,-8.8,-11.2,0,1.1,1.1,1,1,1,1]]],"path":"scene/buttons/btn_m2_opt5","instances":[[0,null]]},{"labels":[],"type":"clip","resources":["scene/buttons/btn_opt6"],"frames":[[[0,-6.25,-8.25,0,1,1,1,1,1,1]],[[0,-9.2,-11.2,0,1.1,1.1,1,1,1,1]]],"path":"scene/buttons/btn_m2_opt6","instances":[[0,null]]},{"labels":[],"type":"clip","resources":["scene/buttons/btn_opt7"],"frames":[[[0,-6.25,-8.3,0,1,1,1,1,1,1]],[[0,-9.2,-11.25,0,1.1,1.1,1,1,1,1]]],"path":"scene/buttons/btn_m2_opt7","instances":[[0,null]]},{"type":"sprite","labels":[],"frames":[[1592,1664,69,69,5,5]],"path":"scene/buttons/btn_opt1","hd":false},{"type":"sprite","labels":[],"frames":[[1868,927,69,69,5,5]],"path":"scene/buttons/btn_opt2","hd":false},{"type":"sprite","labels":[],"frames":[[1939,927,69,69,5,5]],"path":"scene/buttons/btn_opt3","hd":false},{"type":"sprite","labels":[],"frames":[[1805,1664,69,69,5,5]],"path":"scene/buttons/btn_opt4","hd":false},{"type":"sprite","labels":[],"frames":[[1663,1664,69,69,5,5]],"path":"scene/buttons/btn_opt5","hd":false},{"type":"sprite","labels":[],"frames":[[1947,1664,69,69,5,5]],"path":"scene/buttons/btn_opt6","hd":false},{"type":"sprite","labels":[],"frames":[[1876,1664,69,69,5,5]],"path":"scene/buttons/btn_opt7","hd":false},{"type":"sprite","labels":[],"frames":[[1076,1440,144,148,72,74]],"path":"scene/chyvaki","hd":false},{"labels":[],"type":"clip","resources":["scene/eyes/eye21","scene/eyes/eye22","scene/eyes/eye23"],"frames":[[[0,0,0,0,1,1,1,1,1,1]],[[0,0,0,0,1,1,1,1,1,1]],[[0,0,0,0,1,1,1,1,1,1]],[[0,0,0,0,1,1,1,1,1,1]],[[0,0,0,0,1,1,1,1,1,1]],[[0,0,0,0,1,1,1,1,1,1]],[[0,0,0,0,1,1,1,1,1,1]],[[0,0,0,0,1,1,1,1,1,1]],[[0,0,0,0,1,1,1,1,1,1]],[[0,0,0,0,1,1,1,1,1,1]],[[0,0,0,0,1,1,1,1,1,1]],[[0,0,0,0,1,1,1,1,1,1]],[[0,0,0,0,1,1,1,1,1,1]],[[0,0,0,0,1,1,1,1,1,1]],[[0,0,0,0,1,1,1,1,1,1]],[[0,0,0,0,1,1,1,1,1,1]],[[0,0,0,0,1,1,1,1,1,1]],[[0,0,0,0,1,1,1,1,1,1]],[[0,0,0,0,1,1,1,1,1,1]],[[0,0,0,0,1,1,1,1,1,1]],[[0,0,0,0,1,1,1,1,1,1]],[[0,0,0,0,1,1,1,1,1,1]],[[0,0,0,0,1,1,1,1,1,1]],[[0,0,0,0,1,1,1,1,1,1]],[[0,0,0,0,1,1,1,1,1,1]],[[0,0,0,0,1,1,1,1,1,1]],[[0,0,0,0,1,1,1,1,1,1]],[[0,0,0,0,1,1,1,1,1,1]],[[0,0,0,0,1,1,1,1,1,1]],[[0,0,0,0,1,1,1,1,1,1]],[[0,0,0,0,1,1,1,1,1,1]],[[0,0,0,0,1,1,1,1,1,1]],[[0,0,0,0,1,1,1,1,1,1]],[[0,0,0,0,1,1,1,1,1,1]],[[0,0,0,0,1,1,1,1,1,1]],[[0,0,0,0,1,1,1,1,1,1]],[[0,0,0,0,1,1,1,1,1,1]],[[0,0,0,0,1,1,1,1,1,1]],[[0,0,0,0,1,1,1,1,1,1]],[[0,0,0,0,1,1,1,1,1,1]],[[0,0,0,0,1,1,1,1,1,1]],[[0,0,0,0,1,1,1,1,1,1]],[[0,0,0,0,1,1,1,1,1,1]],[[0,0,0,0,1,1,1,1,1,1]],[[0,0,0,0,1,1,1,1,1,1]],[[0,0,0,0,1,1,1,1,1,1]],[[0,0,0,0,1,1,1,1,1,1]],[[0,0,0,0,1,1,1,1,1,1]],[[0,0,0,0,1,1,1,1,1,1]],[[0,0,0,0,1,1,1,1,1,1]],[[0,0,0,0,1,1,1,1,1,1]],[[0,0,0,0,1,1,1,1,1,1]],[[0,0,0,0,1,1,1,1,1,1]],[[0,0,0,0,1,1,1,1,1,1]],[[0,0,0,0,1,1,1,1,1,1]],[[0,0,0,0,1,1,1,1,1,1]],[[0,0,0,0,1,1,1,1,1,1]],[[0,0,0,0,1,1,1,1,1,1]],[[0,0,0,0,1,1,1,1,1,1]],[[1,0,0,0,1,1,1,1,1,1]],[[1,0,0,0,1,1,1,1,1,1]],[[2,0,0,0,1,1,1,1,1,1]],[[2,0,0,0,1,1,1,1,1,1]],[[3,0,0,0,1,1,1,1,1,1]],[[3,0,0,0,1,1,1,1,1,1]],[[4,0,0,0,1,1,1,1,1,1]],[[4,0,0,0,1,1,1,1,1,1]],[[4,0,0,0,1,1,1,1,1,1]],[[4,0,0,0,1,1,1,1,1,1]],[[4,0,0,0,1,1,1,1,1,1]],[[4,0,0,0,1,1,1,1,1,1]],[[4,0,0,0,1,1,1,1,1,1]],[[4,0,0,0,1,1,1,1,1,1]],[[4,0,0,0,1,1,1,1,1,1]],[[4,0,0,0,1,1,1,1,1,1]],[[4,0,0,0,1,1,1,1,1,1]],[[4,0,0,0,1,1,1,1,1,1]],[[4,0,0,0,1,1,1,1,1,1]],[[4,0,0,0,1,1,1,1,1,1]],[[4,0,0,0,1,1,1,1,1,1]],[[4,0,0,0,1,1,1,1,1,1]],[[4,0,0,0,1,1,1,1,1,1]],[[4,0,0,0,1,1,1,1,1,1]],[[4,0,0,0,1,1,1,1,1,1]],[[4,0,0,0,1,1,1,1,1,1]],[[4,0,0,0,1,1,1,1,1,1]],[[4,0,0,0,1,1,1,1,1,1]],[[4,0,0,0,1,1,1,1,1,1]],[[4,0,0,0,1,1,1,1,1,1]],[[4,0,0,0,1,1,1,1,1,1]],[[4,0,0,0,1,1,1,1,1,1]],[[4,0,0,0,1,1,1,1,1,1]],[[4,0,0,0,1,1,1,1,1,1]],[[4,0,0,0,1,1,1,1,1,1]],[[4,0,0,0,1,1,1,1,1,1]],[[4,0,0,0,1,1,1,1,1,1]],[[4,0,0,0,1,1,1,1,1,1]],[[4,0,0,0,1,1,1,1,1,1]],[[4,0,0,0,1,1,1,1,1,1]],[[4,0,0,0,1,1,1,1,1,1]]],"path":"scene/eyes/eye2","instances":[[0,null],[1,null],[2,null],[1,null],[0,null]]},{"type":"sprite","labels":[],"frames":[[0,0,0,0,0,0]],"path":"scene/eyes/eye21","hd":false},{"type":"sprite","labels":[],"frames":[[0,0,0,0,0,0]],"path":"scene/eyes/eye22","hd":false},{"type":"sprite","labels":[],"frames":[[0,0,0,0,0,0]],"path":"scene/eyes/eye23","hd":false},{"type":"sprite","labels":[],"frames":[[1525,1,252,480,-1,0]],"path":"scene/model1/m1_body","hd":false},{"type":"sprite","labels":[],"frames":[[805,1664,72,86,0,0]],"path":"scene/model1/m1_head","hd":false},{"labels":[],"type":"clip","resources":["scene/model1/opt_3","scene/model1/m1_body","scene/model1/m1_head","scene/model1/opt_2","scene/model1/opt_5","scene/model1/opt_6","scene/model1/opt_1","scene/model1/opt_4","scene/model1/opt_7"],"frames":[[[0,337.1,-81.15,0,1,1,1,1,1,1],[1,74.35,-2,0,1,1,1,1,1,1],[2,165.05,-48.45,-0.36185,1.0281,1.0281,1,1,1,1],[3,130.55,1.85,0,1,1,1,1,1,1],[4,133.25,386,0,1,1,1,1,1,1],[5,-328.05,124.5,0,1,1,1,1,1,1],[6,170.6,-70.55,0,1,1,1,1,1,1],[7,163.55,-83.45,0,1,1,1,1,1,1],[8,234.65,9.65,0,1,1,1,1,1,1]]],"path":"scene/model1/model1","instances":[[0,"opt_3"],[1,null],[2,null],[3,"opt_2"],[4,"opt_5"],[5,"opt_6"],[6,"opt_1"],[7,"opt_4"],[8,"opt_7"]]},{"type":"sprite","labels":[{"frame":0,"name":"default_frame"}],"frames":[[404,1664,85,92,0,0],[1915,483,93,104,3,1],[491,1664,69,92,-12,0],[879,1664,73,84,-7,-4],[642,1664,80,88,-5,-3],[1,1774,79,65,-5,-1],[562,1664,78,91,-4,-4]],"path":"scene/model1/opt_1","hd":false},{"type":"sprite","labels":[{"frame":0,"name":"default_frame"}],"frames":[[440,613,196,422,0,0],[1410,613,191,399,-3,-28],[1603,613,194,396,-1,-29],[1022,613,191,400,-6,-23],[1215,613,193,400,-5,-22],[0,0,0,0,0,0]],"path":"scene/model1/opt_2","hd":false},{"type":"sprite","labels":[],"frames":[[638,613,382,417,81,10],[1,1664,260,108,61,-261],[314,1083,292,346,66,-8],[1220,1083,222,281,-2,-112],[1,613,437,468,170,22],[0,0,0,0,0,0]],"path":"scene/model1/opt_3","hd":false},{"type":"sprite","labels":[],"frames":[[1926,296,106,122,0,0],[1926,1,69,157,-3,11],[724,1664,79,88,-12,-24],[824,1440,126,184,6,-3],[1393,1440,157,136,8,0],[1620,483,102,112,-2,-4],[0,0,0,0,0,0]],"path":"scene/model1/opt_4","hd":false},{"type":"sprite","labels":[{"frame":0,"name":"default_frame"}],"frames":[[263,1664,139,95,0,0],[1399,1664,191,69,44,-46],[1108,1774,126,46,-3,-39],[1222,1440,169,146,24,52],[823,1037,121,33,-7,-53],[0,0,0,0,0,0]],"path":"scene/model1/opt_5","hd":false},{"type":"sprite","labels":[{"frame":0,"name":"default_frame"}],"frames":[[440,1037,45,44,-508,146],[1236,1774,42,46,-510,148],[1327,1774,41,45,-511,146],[1280,1774,45,45,-507,147],[1062,1774,44,46,-509,150],[949,1774,46,52,-506,152]],"path":"scene/model1/opt_6","hd":false},{"type":"sprite","labels":[{"frame":0,"name":"default_frame"}],"frames":[[171,1440,211,219,95,-4],[608,1083,307,304,130,38],[917,1083,301,297,103,58],[1723,1083,225,262,95,39],[1444,1083,277,273,95,50],[384,1440,225,201,95,-22],[611,1440,211,198,95,-25]],"path":"scene/model1/opt_7","hd":false},{"type":"sprite","labels":[],"frames":[[1779,1,145,454,29,-92]],"path":"scene/model2/m2_body","hd":false},{"type":"sprite","labels":[],"frames":[[946,1037,45,27,0,0]],"path":"scene/model2/m2_hand1","hd":false},{"type":"sprite","labels":[],"frames":[[2010,527,22,26,0,0]],"path":"scene/model2/m2_hand2","hd":false},{"type":"sprite","labels":[],"frames":[[1921,1440,71,97,-4,-15]],"path":"scene/model2/m2_head","hd":false},{"labels":[],"type":"clip","resources":["scene/model2/m2_head","scene/eyes/eye2","scene/model2/opt_1","scene/model2/m2_hand2","scene/model2/opt_7","scene/model2/m2_body","scene/model2/m2_hand1","scene/model2/opt_5","scene/model2/opt_2","scene/model2/opt_3","scene/model2/opt_4","scene/model2/opt_6"],"frames":[[[0,10.65,-125.95,-0.026935,1,1,1,1,1,1],[1,15.6,-71.35,0,1,1,1,1,1,1],[2,364.45,58.05,0,1,1,1,1,1,1],[3,97.5,165.7,0,1,1,1,1,1,1],[4,364.45,161.25,0,1,1,1,1,1,1],[5,11.85,-123.2,0,1,1,1,1,1,1],[6,38.9,-22.1,3.1148,0.99998,-0.99998,1,1,1,1],[7,364.45,126.85,0,1,1,1,1,1,1],[8,364.45,75.25,0,1,1,1,1,1,1],[9,364.45,92.45,0,1,1,1,1,1,1],[10,364.45,109.65,0,1,1,1,1,1,1],[11,364.45,144.05,0,1,1,1,1,1,1]]],"path":"scene/model2/model2","instances":[[0,null],[1,null],[2,"opt_1"],[3,null],[4,"opt_7"],[5,null],[6,null],[7,"opt_5"],[8,"opt_2"],[9,"opt_3"],[10,"opt_4"],[11,"opt_6"]]},{"type":"sprite","labels":[{"frame":0,"name":"default_frame"}],"frames":[[0,0,0,0,0,0],[0,0,0,0,0,0],[0,0,0,0,0,0],[2033,18,6,12,276,104],[0,0,0,0,0,0],[0,0,0,0,0,0]],"path":"scene/model2/opt_1","hd":false},{"type":"sprite","labels":[{"frame":1,"name":"default_frame"}],"frames":[[0,0,0,0,0,0],[0,0,0,0,0,0],[0,0,0,0,0,0],[0,0,0,0,0,0],[0,0,0,0,0,0],[0,0,0,0,0,0],[0,0,0,0,0,0],[0,0,0,0,0,0],[0,0,0,0,0,0]],"path":"scene/model2/opt_2","hd":false},{"type":"sprite","labels":[],"frames":[[0,0,0,0,0,0],[0,0,0,0,0,0],[0,0,0,0,0,0],[0,0,0,0,0,0],[1525,483,93,114,360,-7],[0,0,0,0,0,0],[0,0,0,0,0,0],[0,0,0,0,0,0]],"path":"scene/model2/opt_3","hd":false},{"type":"sprite","labels":[],"frames":[[0,0,0,0,0,0],[0,0,0,0,0,0],[0,0,0,0,0,0],[0,0,0,0,0,0],[0,0,0,0,0,0],[0,0,0,0,0,0],[0,0,0,0,0,0]],"path":"scene/model2/opt_4","hd":false},{"type":"sprite","labels":[{"frame":0,"name":"default_frame"}],"frames":[[0,0,0,0,0,0],[0,0,0,0,0,0],[0,0,0,0,0,0],[0,0,0,0,0,0],[0,0,0,0,0,0],[0,0,0,0,0,0],[0,0,0,0,0,0],[0,0,0,0,0,0]],"path":"scene/model2/opt_5","hd":false},{"type":"sprite","labels":[{"frame":0,"name":"default_frame"}],"frames":[[0,0,0,0,0,0],[1997,1,34,116,324,156],[1798,457,20,20,264,-1],[0,0,0,0,0,0],[0,0,0,0,0,0]],"path":"scene/model2/opt_6","hd":false},{"type":"sprite","labels":[{"frame":0,"name":"default_frame"}],"frames":[[0,0,0,0,0,0],[1950,1184,87,98,281,-20],[1950,1083,80,99,287,-15],[1926,160,105,134,298,-14],[1799,927,67,77,282,-15]],"path":"scene/model2/opt_7","hd":false},{"type":"sprite","labels":[],"frames":[[1,1440,168,222,84,111]],"path":"scene/monstr_01","hd":false},{"type":"sprite","labels":[],"frames":[[1,1083,311,355,159,184]],"path":"scene/monstr_02","hd":false},{"type":"sprite","labels":[],"frames":[[613,1037,46,36,10,9],[1997,119,50,39,12,10]],"path":"scene/panel/back_btn","hd":false},{"type":"sprite","labels":[],"frames":[[401,1774,56,56,11,11],[845,1774,54,54,10,10]],"path":"scene/panel/btn_fb","hd":false},{"type":"sprite","labels":[],"frames":[[997,1774,63,51,7,7],[592,1774,63,54,7,10]],"path":"scene/panel/btn_photo","hd":false},{"type":"sprite","labels":[],"frames":[[1959,420,76,34,11,1],[739,1037,82,34,14,3]],"path":"scene/panel/btn_reset","hd":false},{"labels":[{"frame":0,"name":"html"},{"frame":1,"name":"flash_photo"}],"type":"clip","resources":["scene/panel/btn_fb","scene/panel/small_logo_box","scene/panel/btn_photo","scene/panel/btn_reset","scene/panel/save_btn","scene/panel/back_btn"],"frames":[[[0,63,105,0,1,1,1,1,1,1],[1,-575,107.3,0,1,1.006,1,1,1,1],[2,59,159.75,0,1.0031,1,1,1,1,1],[3,-584,172,0,1.1984,1.1852,1,1,1,1]],[[0,63,105,0,1,1,1,1,1,1],[1,-575,107.3,0,1,1.006,1,1,1,1],[4,-588.1,178.7,0,1.2,1.2,1,1,1,1],[5,-543,643.95,0,1,1,1,1,1,1]]],"path":"scene/panel/controls","instances":[[0,"btn_fb"],[1,"small_logo"],[2,"btn_photo"],[3,"btn_reset"],[4,"btn_save"],[5,"btn_back"]]},{"type":"sprite","labels":[],"frames":[[661,1037,76,34,7,7],[529,1037,82,36,10,8]],"path":"scene/panel/save_btn","hd":false},{"type":"sprite","labels":[],"frames":[[1724,483,189,110,40,24]],"path":"scene/panel/small_logo","hd":false},{"labels":[],"type":"clip","resources":["scene/panel/small_logo","scene/panel/small_logo_light"],"frames":[[[0,-6,6,0,0.60027,0.59999,1,1,1,1],[1,0,0,0,1,1,1,1,1,1]]],"path":"scene/panel/small_logo_box","instances":[[0,"small_logo"],[1,null]]},{"type":"sprite","labels":[],"frames":[[2043,6,3,3,25,2],[1779,457,17,21,27,6],[2010,555,26,26,27,5],[2010,483,34,42,27,6],[901,1774,46,54,27,6],[1994,1440,49,58,24,6],[221,1774,61,58,24,6],[157,1774,62,58,24,6],[1950,1284,76,59,20,7],[459,1774,76,56,10,5],[82,1774,73,58,-2,7],[284,1774,65,58,-10,7],[537,1774,53,56,-24,5],[351,1774,48,56,-30,5],[487,1037,40,44,-39,-7],[1926,420,31,35,-48,-16],[2013,613,19,25,-60,-26],[2033,1,8,15,-71,-36],[2043,1,2,3,-77,-48],[0,0,0,0,0,0],[0,0,0,0,0,0],[0,0,0,0,0,0],[0,0,0,0,0,0],[0,0,0,0,0,0],[0,0,0,0,0,0],[0,0,0,0,0,0],[0,0,0,0,0,0],[0,0,0,0,0,0],[0,0,0,0,0,0],[0,0,0,0,0,0],[0,0,0,0,0,0],[0,0,0,0,0,0],[0,0,0,0,0,0],[0,0,0,0,0,0],[0,0,0,0,0,0],[0,0,0,0,0,0],[0,0,0,0,0,0],[0,0,0,0,0,0],[0,0,0,0,0,0],[0,0,0,0,0,0],[0,0,0,0,0,0],[0,0,0,0,0,0],[0,0,0,0,0,0],[0,0,0,0,0,0],[0,0,0,0,0,0],[0,0,0,0,0,0],[0,0,0,0,0,0],[0,0,0,0,0,0],[0,0,0,0,0,0],[0,0,0,0,0,0],[0,0,0,0,0,0],[0,0,0,0,0,0],[0,0,0,0,0,0],[0,0,0,0,0,0],[0,0,0,0,0,0],[0,0,0,0,0,0],[0,0,0,0,0,0],[0,0,0,0,0,0],[0,0,0,0,0,0],[0,0,0,0,0,0],[0,0,0,0,0,0],[0,0,0,0,0,0],[0,0,0,0,0,0],[0,0,0,0,0,0],[0,0,0,0,0,0],[0,0,0,0,0,0],[0,0,0,0,0,0],[0,0,0,0,0,0],[0,0,0,0,0,0],[0,0,0,0,0,0],[0,0,0,0,0,0],[0,0,0,0,0,0],[0,0,0,0,0,0],[0,0,0,0,0,0],[0,0,0,0,0,0],[0,0,0,0,0,0]],"path":"scene/panel/small_logo_light","hd":false},{"type":"sprite","labels":[],"frames":[[1799,613,212,312,106,156]],"path":"scene/raketa","hd":false},{"type":"sprite","labels":[],"frames":[[1196,1664,201,72,98,38]],"path":"scene/sauron","hd":false},{"labels":[],"type":"clip","resources":["scene/back","scene/model1/model1","scene/buttons/btn_m1_opt1","scene/buttons/btn_m1_opt2","scene/buttons/btn_m1_opt3","scene/buttons/btn_m1_opt4","scene/buttons/btn_m1_opt5","scene/buttons/btn_m1_opt6","scene/buttons/btn_m1_opt7","scene/buttons/btn_m2_opt1","scene/buttons/btn_m2_opt2","scene/buttons/btn_m2_opt3","scene/buttons/btn_m2_opt4","scene/buttons/btn_m2_opt5","scene/buttons/btn_m2_opt6","scene/buttons/btn_m2_opt7","scene/buttons/btn_back","scene/panel/controls"],"frames":[[[0,0,0,0,1,1,1,1,1,1],[1,189.2,101.6,0,1,1,1,1,1,1],[2,13.65,455.55,0,1.0405,1.0405,1,1,1,1],[3,190.7,539.1,0,1.0396,1.0396,1,1,1,1],[4,593.6,539.9,0,1.0396,1.0396,1,1,1,1],[5,682.05,455.6,0,1.0396,1.0396,1,1,1,1],[6,107.15,539.1,0,1.0396,1.0396,1,1,1,1],[7,13.65,539.2,0,1.0396,1.0396,1,1,1,1],[8,500.1,540,0,1.0396,1.0396,1,1,1,1],[9,818.85,27,0,0.74719,0.74719,1,1,1,1],[10,817.75,93.55,0,0.74719,0.74719,1,1,1,1],[11,819.25,226.65,0,0.74719,0.74719,1,1,1,1],[12,819.05,160.1,0,0.74719,0.74719,1,1,1,1],[13,818.85,293.2,0,0.74719,0.74719,1,1,1,1],[14,819.15,359.75,0,0.74718,0.74718,1,1,1,1],[15,819.15,426.45,0,0.74718,0.74718,1,1,1,1],[16,687.6,546.35,0,1.0396,1.0396,1,1,1,1],[17,620.4,-78.85,0,1,1,1,1,1,1]]],"path":"scene/scene_screen","instances":[[0,"back_1"],[1,"model_1"],[2,"btn_m1_opt1"],[3,"btn_m1_opt2"],[4,"btn_m1_opt3"],[5,"btn_m1_opt4"],[6,"btn_m1_opt5"],[7,"btn_m1_opt6"],[8,"btn_m1_opt7"],[9,"btn_m2_opt1"],[10,"btn_m2_opt2"],[11,"btn_m2_opt3"],[12,"btn_m2_opt4"],[13,"btn_m2_opt5"],[14,"btn_m2_opt6"],[15,"btn_m2_opt7"],[16,"btnBackground"],[17,"controls"]]},{"type":"sprite","labels":[],"frames":[[952,1440,122,172,61,86]],"path":"scene/tarilka","hd":false}]